<?xml version="1.0" encoding="utf-8" standalone="yes"?>
<selections>
  <!-- <selection displayName = "Recommended Mods For New Users">Recommended Mods.xml</selection> -->
  <selection displayName = "Willster419 (XVM)">willster419.xml</selection>
  <selection displayName = "Willster419 (no XVM)">willster419_noXVM.xml</selection>
  <selection displayName = "elektrosmoker">elektrosmoker.xml</selection>
  <selection displayName = "123gauss">123gauss.xml</selection>
  <selection displayName = "dirty20067">dirty20067.xml</selection>
  <!-- <selection displayName = "nuclearguy931">nuclearguy931.xml</selection> -->
  <selection displayName = "The Illusion">TheIllusion.xml</selection>
</selections>